chesnut/__init__.py
chesnut/node.py
chesnut-1.0.1.dist-info/LICENSE
chesnut-1.0.1.dist-info/METADATA
chesnut-1.0.1.dist-info/WHEEL
chesnut-1.0.1.dist-info/top_level.txt
chesnut-1.0.1.dist-info/RECORD
