Metadata-Version: 2.1
Name: chesnut
Version: 1.0.1
Summary: A lightweight tree class implementation, with a focus on searching for nodes based on their type.
Author-email: Matt Mitchell <matt.mitchell97@hotmail.com>
License: MIT License
Project-URL: Documentation, https://m4ttm.github.io/chesnut
Project-URL: Repository, https://github.com/m4ttm/chesnut
Project-URL: Issues, https://github.com/m4ttm/chesnut/issues
License-File: LICENSE
Requires-Dist: pdoc >=14.4.0
Requires-Dist: pylint >=2.17.7
Requires-Dist: pytest >=7.4.2
Requires-Dist: pytest-func-cov >=0.2.3
